{"playerCards":[{"cost":3,"imageID":999,"effect":DRAW_CARD,"name":"Spell","id":466811350,"type":"class Interface.Cards.SpellCard"},{"etbEffect":"Taunt","cost":3,"imageID":29,"name":"Minion","power":6,"id":298372372,"toughness":3,"deathEffect":"NONE","type":"class Interface.Cards.CreatureCard"},{"etbEffect":"Taunt","cost":6,"imageID":45,"name":"Minion","power":4,"id":258307427,"toughness":1,"deathEffect":"NONE","type":"class Interface.Cards.CreatureCard"},{"etbEffect":"Buff_Power","cost":1,"imageID":27,"name":"Minion","power":4,"id":1598582738,"toughness":7,"deathEffect":"NONE","type":"class Interface.Cards.CreatureCard"},{"etbEffect":"NONE","cost":7,"imageID":31,"name":"Minion","power":6,"id":2085775257,"toughness":1,"deathEffect":"NONE","type":"class Interface.Cards.CreatureCard"},{"etbEffect":"NONE","cost":1,"imageID":38,"name":"Minion","power":5,"id":204474968,"toughness":6,"deathEffect":"Gain_Life","type":"class Interface.Cards.CreatureCard"},{"etbEffect":"Buff_Power","cost":5,"imageID":11,"name":"Minion","power":3,"id":1367284841,"toughness":4,"deathEffect":"NONE","type":"class Interface.Cards.CreatureCard"},{"etbEffect":"NONE","cost":7,"imageID":37,"name":"Minion","power":4,"id":1417575130,"toughness":4,"deathEffect":"NONE","type":"class Interface.Cards.CreatureCard"},{"cost":2,"imageID":999,"effect":DRAW_CARD,"name":"Spell","id":878915428,"type":"class Interface.Cards.SpellCard"},{"etbEffect":"Taunt","cost":1,"imageID":17,"name":"Minion","power":4,"id":1898048740,"toughness":7,"deathEffect":"NONE","type":"class Interface.Cards.CreatureCard"},{"etbEffect":"NONE","cost":1,"imageID":23,"name":"Minion","power":1,"id":1011831088,"toughness":1,"deathEffect":"Gain_Life","type":"class Interface.Cards.CreatureCard"},{"etbEffect":"Taunt","cost":5,"imageID":11,"name":"Minion","power":5,"id":768027415,"toughness":3,"deathEffect":"NONE","type":"class Interface.Cards.CreatureCard"},{"etbEffect":"Buff_Power","cost":1,"imageID":41,"name":"Minion","power":7,"id":1853542514,"toughness":3,"deathEffect":"NONE","type":"class Interface.Cards.CreatureCard"},{"etbEffect":"NONE","cost":3,"imageID":24,"name":"Minion","power":3,"id":329583000,"toughness":1,"deathEffect":"Gain_Life","type":"class Interface.Cards.CreatureCard"},{"etbEffect":"NONE","cost":3,"imageID":43,"name":"Minion","power":6,"id":151093031,"toughness":4,"deathEffect":"Gain_Life","type":"class Interface.Cards.CreatureCard"},{"cost":1,"imageID":999,"effect":DRAW_CARD,"name":"Spell","id":478128980,"type":"class Interface.Cards.SpellCard"},{"etbEffect":"NONE","cost":1,"imageID":40,"name":"Minion","power":1,"id":1360042204,"toughness":5,"deathEffect":"NONE","type":"class Interface.Cards.CreatureCard"},{"cost":4,"imageID":666,"effect":DEAL_DAMAGE,"name":"Spell","id":467406108,"type":"class Interface.Cards.SpellCard"},{"etbEffect":"NONE","cost":6,"imageID":19,"name":"Minion","power":2,"id":2144445364,"toughness":4,"deathEffect":"Gain_Life","type":"class Interface.Cards.CreatureCard"},{"etbEffect":"NONE","cost":4,"imageID":16,"name":"Minion","power":3,"id":1205238998,"toughness":3,"deathEffect":"NONE","type":"class Interface.Cards.CreatureCard"},{"etbEffect":"NONE","cost":1,"imageID":13,"name":"Minion","power":2,"id":600159124,"toughness":4,"deathEffect":"Gain_Life","type":"class Interface.Cards.CreatureCard"},{"etbEffect":"Taunt","cost":4,"imageID":32,"name":"Minion","power":5,"id":743887240,"toughness":5,"deathEffect":"Gain_Life","type":"class Interface.Cards.CreatureCard"},{"cost":3,"imageID":999,"effect":DRAW_CARD,"name":"Spell","id":2042931797,"type":"class Interface.Cards.SpellCard"},{"cost":2,"imageID":999,"effect":DRAW_CARD,"name":"Spell","id":1075456489,"type":"class Interface.Cards.SpellCard"},{"etbEffect":"Taunt","cost":5,"imageID":27,"name":"Minion","power":5,"id":2143264363,"toughness":7,"deathEffect":"Gain_Life","type":"class Interface.Cards.CreatureCard"},{"etbEffect":"Buff_Power","cost":7,"imageID":18,"name":"Minion","power":5,"id":2030705432,"toughness":5,"deathEffect":"Gain_Life","type":"class Interface.Cards.CreatureCard"},{"cost":1,"imageID":999,"effect":DRAW_CARD,"name":"Spell","id":506401093,"type":"class Interface.Cards.SpellCard"},{"cost":5,"imageID":999,"effect":DRAW_CARD,"name":"Spell","id":1140639554,"type":"class Interface.Cards.SpellCard"},{"etbEffect":"NONE","cost":2,"imageID":31,"name":"Minion","power":7,"id":35370820,"toughness":4,"deathEffect":"NONE","type":"class Interface.Cards.CreatureCard"},{"etbEffect":"NONE","cost":2,"imageID":14,"name":"Minion","power":2,"id":1995771747,"toughness":2,"deathEffect":"NONE","type":"class Interface.Cards.CreatureCard"},{"cost":2,"imageID":999,"effect":DRAW_CARD,"name":"Spell","id":573924225,"type":"class Interface.Cards.SpellCard"},{"etbEffect":"Taunt","cost":2,"imageID":8,"name":"Minion","power":7,"id":464320928,"toughness":7,"deathEffect":"Gain_Life","type":"class Interface.Cards.CreatureCard"},{"etbEffect":"Taunt","cost":6,"imageID":8,"name":"Minion","power":6,"id":505384944,"toughness":5,"deathEffect":"NONE","type":"class Interface.Cards.CreatureCard"},{"etbEffect":"Taunt","cost":7,"imageID":36,"name":"Minion","power":7,"id":185510770,"toughness":5,"deathEffect":"Gain_Life","type":"class Interface.Cards.CreatureCard"},{"etbEffect":"NONE","cost":7,"imageID":28,"name":"Minion","power":2,"id":1243953247,"toughness":5,"deathEffect":"NONE","type":"class Interface.Cards.CreatureCard"},{"etbEffect":"NONE","cost":6,"imageID":20,"name":"Minion","power":2,"id":1328393678,"toughness":3,"deathEffect":"Gain_Life","type":"class Interface.Cards.CreatureCard"},{"etbEffect":"NONE","cost":2,"imageID":31,"name":"Minion","power":5,"id":1176620123,"toughness":3,"deathEffect":"Gain_Life","type":"class Interface.Cards.CreatureCard"},{"cost":7,"imageID":666,"effect":DEAL_DAMAGE,"name":"Spell","id":1772966496,"type":"class Interface.Cards.SpellCard"},{"etbEffect":"Buff_Power","cost":5,"imageID":33,"name":"Minion","power":2,"id":10131958,"toughness":5,"deathEffect":"NONE","type":"class Interface.Cards.CreatureCard"},{"etbEffect":"Buff_Power","cost":1,"imageID":28,"name":"Minion","power":2,"id":669641341,"toughness":7,"deathEffect":"Gain_Life","type":"class Interface.Cards.CreatureCard"},{"etbEffect":"Taunt","cost":2,"imageID":29,"name":"Minion","power":3,"id":803999518,"toughness":7,"deathEffect":"Gain_Life","type":"class Interface.Cards.CreatureCard"},{"etbEffect":"Taunt","cost":4,"imageID":4,"name":"Minion","power":2,"id":705633244,"toughness":5,"deathEffect":"NONE","type":"class Interface.Cards.CreatureCard"},{"cost":6,"imageID":666,"effect":DEAL_DAMAGE,"name":"Spell","id":297492028,"type":"class Interface.Cards.SpellCard"},{"etbEffect":"Buff_Power","cost":6,"imageID":6,"name":"Minion","power":4,"id":51848854,"toughness":2,"deathEffect":"NONE","type":"class Interface.Cards.CreatureCard"},{"cost":2,"imageID":666,"effect":DEAL_DAMAGE,"name":"Spell","id":1032849740,"type":"class Interface.Cards.SpellCard"},{"etbEffect":"NONE","cost":6,"imageID":40,"name":"Minion","power":3,"id":1793473929,"toughness":7,"deathEffect":"NONE","type":"class Interface.Cards.CreatureCard"},{"cost":3,"imageID":666,"effect":DEAL_DAMAGE,"name":"Spell","id":366056467,"type":"class Interface.Cards.SpellCard"},{"cost":7,"imageID":999,"effect":DRAW_CARD,"name":"Spell","id":370938966,"type":"class Interface.Cards.SpellCard"},{"etbEffect":"Taunt","cost":4,"imageID":24,"name":"Minion","power":7,"id":971178192,"toughness":1,"deathEffect":"Gain_Life","type":"class Interface.Cards.CreatureCard"},{"etbEffect":"NONE","cost":3,"imageID":17,"name":"Minion","power":5,"id":1449307757,"toughness":6,"deathEffect":"NONE","type":"class Interface.Cards.CreatureCard"},{"etbEffect":"Taunt","cost":1,"imageID":17,"name":"Minion","power":6,"id":1599610487,"toughness":5,"deathEffect":"Gain_Life","type":"class Interface.Cards.CreatureCard"},{"cost":5,"imageID":666,"effect":DEAL_DAMAGE,"name":"Spell","id":506263776,"type":"class Interface.Cards.SpellCard"},{"etbEffect":"NONE","cost":2,"imageID":38,"name":"Minion","power":1,"id":1668871233,"toughness":4,"deathEffect":"NONE","type":"class Interface.Cards.CreatureCard"},{"cost":6,"imageID":666,"effect":DEAL_DAMAGE,"name":"Spell","id":1438310457,"type":"class Interface.Cards.SpellCard"},{"etbEffect":"NONE","cost":2,"imageID":34,"name":"Minion","power":5,"id":389516136,"toughness":3,"deathEffect":"NONE","type":"class Interface.Cards.CreatureCard"},{"etbEffect":"Taunt","cost":4,"imageID":4,"name":"Minion","power":2,"id":1853176449,"toughness":7,"deathEffect":"Gain_Life","type":"class Interface.Cards.CreatureCard"},{"cost":3,"imageID":999,"effect":DRAW_CARD,"name":"Spell","id":644954674,"type":"class Interface.Cards.SpellCard"},{"cost":1,"imageID":666,"effect":DEAL_DAMAGE,"name":"Spell","id":2061544057,"type":"class Interface.Cards.SpellCard"},{"cost":5,"imageID":999,"effect":DRAW_CARD,"name":"Spell","id":1617723874,"type":"class Interface.Cards.SpellCard"},{"etbEffect":"NONE","cost":6,"imageID":3,"name":"Minion","power":2,"id":406174452,"toughness":5,"deathEffect":"Gain_Life","type":"class Interface.Cards.CreatureCard"}]}